autovid/__init__.py
autovid/api_keys.py
autovid/exceptions.py
autovid/functionality.py
autovid/utils/__init__.py
autovid/utils/clip.py
autovid/utils/reddit_handler.py
tests/__init__.py
tests/test_reddit_handler.py
autovid-0.0.2.dist-info/METADATA
autovid-0.0.2.dist-info/WHEEL
autovid-0.0.2.dist-info/top_level.txt
autovid-0.0.2.dist-info/RECORD
